luigine/__init__.py
luigine/abc.py
luigine/utils.py
luigine-1.4.1.dist-info/LICENSE
luigine-1.4.1.dist-info/METADATA
luigine-1.4.1.dist-info/WHEEL
luigine-1.4.1.dist-info/top_level.txt
luigine-1.4.1.dist-info/RECORD
